LICENSE
MANIFEST.in
README.md
gitlab_wrapper.py
setup.py
gitlab_wrapper.egg-info/PKG-INFO
gitlab_wrapper.egg-info/SOURCES.txt
gitlab_wrapper.egg-info/dependency_links.txt
gitlab_wrapper.egg-info/requires.txt
gitlab_wrapper.egg-info/top_level.txt