Metadata-Version: 1.1
Name: gitlab-wrapper
Version: 0.0.2
Summary: UNKNOWN
Home-page: https://github.com/suguby/gitlab_wrapper
Author: Shandrinov Vadim
Author-email: suguby@gmail.com
License: BSD License
Keywords: git gitlab skillbox
Platform: UNKNOWN
Classifier: Development Status :: 4 - Beta
Classifier: License :: OSI Approved :: BSD License
Classifier: Intended Audience :: Education
Classifier: Operating System :: Microsoft :: Windows
Classifier: Operating System :: POSIX :: Linux
Classifier: Topic :: Education
Classifier: Programming Language :: Python
Classifier: Programming Language :: Python :: 3.5
